{"region": {"center": {"latitude": 40.70544486444615, "longitude": -73.99429321289062}}, "businesses": [{"transactions": [], "distance": 4705.64498173, "price": "$", "display_phone": "(718) 768-0131", "phone": "+17187680131", "url": "https://www.yelp.com/biz/freddys-bar-brooklyn-2?adjust_creative=gBcvfFpabk3CnzmXKdYe3w&utm_campaign=yelp_api_v3&utm_medium=api_v3_business_search&utm_source=gBcvfFpabk3CnzmXKdYe3w", "name": "Freddy's Bar", "location": {"display_address": ["627 5th Ave", "Brooklyn, NY 11215"], "country": "US", "state": "NY", "address3": "", "address2": "", "address1": "627 5th Ave", "city": "Brooklyn", "zip_code": "11215"}, "is_closed": false, "review_count": 182, "coordinates": {"latitude": 40.6631969, "longitude": -73.991061}, "id": "freddys-bar-brooklyn-2", "image_url": "https://s3-media1.fl.yelpcdn.com/bphoto/Ev4wyPjzob40ksS_rw9ncg/o.jpg", "categories": [{"alias": "bars", "title": "Bars"}, {"alias": "musicvenues", "title": "Music Venues"}], "rating": 4.5}, {"transactions": [], "distance": 4314.586788044, "price": "$$$", "display_phone": "(212) 776-1990", "phone": "+12127761990", "url": "https://www.yelp.com/biz/salinas-new-york?adjust_creative=gBcvfFpabk3CnzmXKdYe3w&utm_campaign=yelp_api_v3&utm_medium=api_v3_business_search&utm_source=gBcvfFpabk3CnzmXKdYe3w", "name": "Salinas", "location": {"display_address": ["136 9th Ave", "New York, NY 10011"], "country": "US", "state": "NY", "address3": "", "address2": "", "address1": "136 9th Ave", "city": "New York", "zip_code": "10011"}, "is_closed": false, "review_count": 745, "coordinates": {"latitude": 40.74364, "longitude": -74.003}, "id": "salinas-new-york", "image_url": "https://s3-media1.fl.yelpcdn.com/bphoto/lw-ZKP-QXdmoPwjxVk1Atw/o.jpg", "categories": [{"alias": "spanish", "title": "Spanish"}], "rating": 4.0}, {"transactions": [], "distance": 2451.858136252, "price": "$$", "display_phone": "(347) 889-5077", "phone": "+13478895077", "url": "https://www.yelp.com/biz/gersi-brooklyn?adjust_creative=gBcvfFpabk3CnzmXKdYe3w&utm_campaign=yelp_api_v3&utm_medium=api_v3_business_search&utm_source=gBcvfFpabk3CnzmXKdYe3w", "name": "Gersi", "location": {"display_address": ["316 Court St", "Brooklyn, NY 11231"], "country": "US", "state": "NY", "address3": "", "address2": "", "address1": "316 Court St", "city": "Brooklyn", "zip_code": "11231"}, "is_closed": false, "review_count": 97, "coordinates": {"latitude": 40.68344, "longitude": -73.99571}, "id": "gersi-brooklyn", "image_url": "https://s3-media3.fl.yelpcdn.com/bphoto/oZzHOcXySkL-tCOFJy20jw/o.jpg", "categories": [{"alias": "italian", "title": "Italian"}, {"alias": "wine_bars", "title": "Wine Bars"}], "rating": 4.5}, {"transactions": ["delivery", "pickup"], "distance": 4432.86426574, "price": "$", "display_phone": "(212) 647-9428", "phone": "+12126479428", "url": "https://www.yelp.com/biz/dil-e-punjab-deli-new-york?adjust_creative=gBcvfFpabk3CnzmXKdYe3w&utm_campaign=yelp_api_v3&utm_medium=api_v3_business_search&utm_source=gBcvfFpabk3CnzmXKdYe3w", "name": "Dil-e Punjab Deli", "location": {"display_address": ["170 9th Ave", "New York, NY 10011"], "country": "US", "state": "NY", "address3": "", "address2": "", "address1": "170 9th Ave", "city": "New York", "zip_code": "10011"}, "is_closed": false, "review_count": 145, "coordinates": {"latitude": 40.7448387145996, "longitude": -74.0020751953125}, "id": "dil-e-punjab-deli-new-york", "image_url": "https://s3-media2.fl.yelpcdn.com/bphoto/vRwVd7qL8DWsvRePyeJaeg/o.jpg", "categories": [{"alias": "indpak", "title": "Indian"}, {"alias": "vegetarian", "title": "Vegetarian"}, {"alias": "pakistani", "title": "Pakistani"}], "rating": 4.5}, {"transactions": [], "distance": 2863.318254986, "price": "$$", "display_phone": "(917) 639-3549", "phone": "+19176393549", "url": "https://www.yelp.com/biz/zundo-ya-new-york?adjust_creative=gBcvfFpabk3CnzmXKdYe3w&utm_campaign=yelp_api_v3&utm_medium=api_v3_business_search&utm_source=gBcvfFpabk3CnzmXKdYe3w", "name": "Zundo-Ya", "location": {"display_address": ["84 E 10th St", "New York, NY 10003"], "country": "US", "state": "NY", "address3": "", "address2": "", "address1": "84 E 10th St", "city": "New York", "zip_code": "10003"}, "is_closed": false, "review_count": 421, "coordinates": {"latitude": 40.7308616638184, "longitude": -73.9899444580078}, "id": "zundo-ya-new-york", "image_url": "https://s3-media2.fl.yelpcdn.com/bphoto/-hdXQ_q-evEDgqvzNcQTTA/o.jpg", "categories": [{"alias": "ramen", "title": "Ramen"}], "rating": 4.0}, {"transactions": [], "distance": 3083.1986777039997, "price": "$$", "display_phone": "(212) 933-0971", "phone": "+12129330971", "url": "https://www.yelp.com/biz/the-pok%C3%A9spot-new-york-3?adjust_creative=gBcvfFpabk3CnzmXKdYe3w&utm_campaign=yelp_api_v3&utm_medium=api_v3_business_search&utm_source=gBcvfFpabk3CnzmXKdYe3w", "name": "The Pok\u00e9Spot", "location": {"display_address": ["120 4th Ave", "New York, NY 10003"], "country": "US", "state": "NY", "address3": "", "address2": null, "address1": "120 4th Ave", "city": "New York", "zip_code": "10003"}, "is_closed": false, "review_count": 401, "coordinates": {"latitude": 40.733097076416, "longitude": -73.9902801513672}, "id": "the-pok\u00e9spot-new-york-3", "image_url": "https://s3-media2.fl.yelpcdn.com/bphoto/7fon0G8yMcEy2RfA4Z1axQ/o.jpg", "categories": [{"alias": "poke", "title": "Poke"}, {"alias": "hawaiian", "title": "Hawaiian"}], "rating": 4.0}, {"transactions": ["delivery", "pickup"], "distance": 2083.0492289999997, "price": "$", "display_phone": "(212) 979-5200", "phone": "+12129795200", "url": "https://www.yelp.com/biz/tuck-shop-new-york?adjust_creative=gBcvfFpabk3CnzmXKdYe3w&utm_campaign=yelp_api_v3&utm_medium=api_v3_business_search&utm_source=gBcvfFpabk3CnzmXKdYe3w", "name": "Tuck Shop", "location": {"display_address": ["68 E 1st St", "New York, NY 10003"], "country": "US", "state": "NY", "address3": "", "address2": "", "address1": "68 E 1st St", "city": "New York", "zip_code": "10003"}, "is_closed": false, "review_count": 348, "coordinates": {"latitude": 40.723716, "longitude": -73.988807}, "id": "tuck-shop-new-york", "image_url": "https://s3-media4.fl.yelpcdn.com/bphoto/W58QK91S0vcwXpehags_Cw/o.jpg", "categories": [{"alias": "australian", "title": "Australian"}], "rating": 4.0}, {"transactions": [], "distance": 1367.98084284, "price": "$$$", "display_phone": "(212) 374-1811", "phone": "+12123741811", "url": "https://www.yelp.com/biz/the-capital-grille-new-york-3?adjust_creative=gBcvfFpabk3CnzmXKdYe3w&utm_campaign=yelp_api_v3&utm_medium=api_v3_business_search&utm_source=gBcvfFpabk3CnzmXKdYe3w", "name": "The Capital Grille", "location": {"display_address": ["120 Broadway", "New York, NY 10271"], "country": "US", "state": "NY", "address3": "", "address2": "", "address1": "120 Broadway", "city": "New York", "zip_code": "10271"}, "is_closed": false, "review_count": 410, "coordinates": {"latitude": 40.7078813982786, "longitude": -74.0102026698364}, "id": "the-capital-grille-new-york-3", "image_url": "https://s3-media1.fl.yelpcdn.com/bphoto/WVNp-ApSvbIAvu7Iggbfrg/o.jpg", "categories": [{"alias": "seafood", "title": "Seafood"}, {"alias": "steak", "title": "Steakhouses"}, {"alias": "wine_bars", "title": "Wine Bars"}], "rating": 4.0}, {"transactions": [], "distance": 2756.666971318, "price": "$$", "display_phone": "(212) 677-2033", "phone": "+12126772033", "url": "https://www.yelp.com/biz/westville-east-new-york-3?adjust_creative=gBcvfFpabk3CnzmXKdYe3w&utm_campaign=yelp_api_v3&utm_medium=api_v3_business_search&utm_source=gBcvfFpabk3CnzmXKdYe3w", "name": "Westville - East", "location": {"display_address": ["173 Ave A", "New York, NY 10009"], "country": "US", "state": "NY", "address3": "", "address2": "", "address1": "173 Ave A", "city": "New York", "zip_code": "10009"}, "is_closed": false, "review_count": 915, "coordinates": {"latitude": 40.728466, "longitude": -73.982131}, "id": "westville-east-new-york-3", "image_url": "https://s3-media4.fl.yelpcdn.com/bphoto/IFJBNJcCXsmxfcdYI6z5Ng/o.jpg", "categories": [{"alias": "tradamerican", "title": "American (Traditional)"}, {"alias": "beerbar", "title": "Beer Bar"}, {"alias": "bakeries", "title": "Bakeries"}], "rating": 4.0}, {"transactions": ["delivery", "pickup"], "distance": 2700.749165546, "price": "$$", "display_phone": "(212) 677-5670", "phone": "+12126775670", "url": "https://www.yelp.com/biz/spot-dessert-bar-new-york-2?adjust_creative=gBcvfFpabk3CnzmXKdYe3w&utm_campaign=yelp_api_v3&utm_medium=api_v3_business_search&utm_source=gBcvfFpabk3CnzmXKdYe3w", "name": "Spot Dessert Bar", "location": {"display_address": ["13 St Marks Pl", "New York, NY 10003"], "country": "US", "state": "NY", "address3": "", "address2": "", "address1": "13 St Marks Pl", "city": "New York", "zip_code": "10003"}, "is_closed": false, "review_count": 2207, "coordinates": {"latitude": 40.72939, "longitude": -73.988923}, "id": "spot-dessert-bar-new-york-2", "image_url": "https://s3-media2.fl.yelpcdn.com/bphoto/4ZEcuAve4pLhHR7rVazO0g/o.jpg", "categories": [{"alias": "desserts", "title": "Desserts"}, {"alias": "macarons", "title": "Macarons"}, {"alias": "creperies", "title": "Creperies"}], "rating": 4.0}, {"transactions": [], "distance": 3358.8409611479997, "price": "$$$", "display_phone": "(212) 691-9700", "phone": "+12126919700", "url": "https://www.yelp.com/biz/decoy-new-york?adjust_creative=gBcvfFpabk3CnzmXKdYe3w&utm_campaign=yelp_api_v3&utm_medium=api_v3_business_search&utm_source=gBcvfFpabk3CnzmXKdYe3w", "name": "Decoy", "location": {"display_address": ["529 Hudson St", "New York, NY 10014"], "country": "US", "state": "NY", "address3": "", "address2": "", "address1": "529 Hudson St", "city": "New York", "zip_code": "10014"}, "is_closed": false, "review_count": 214, "coordinates": {"latitude": 40.734196, "longitude": -74.006519}, "id": "decoy-new-york", "image_url": "https://s3-media4.fl.yelpcdn.com/bphoto/vZIinEo2_oGDXQFxWR5zyQ/o.jpg", "categories": [{"alias": "chinese", "title": "Chinese"}, {"alias": "bars", "title": "Bars"}], "rating": 4.0}, {"transactions": ["delivery", "pickup"], "distance": 1680.2834086819998, "price": "$$", "display_phone": "(212) 966-1883", "phone": "+12129661883", "url": "https://www.yelp.com/biz/luannes-wild-ginger-all-asian-vegan-new-york?adjust_creative=gBcvfFpabk3CnzmXKdYe3w&utm_campaign=yelp_api_v3&utm_medium=api_v3_business_search&utm_source=gBcvfFpabk3CnzmXKdYe3w", "name": "LuAnne's Wild Ginger All-Asian Vegan", "location": {"display_address": ["380 Broome St", "New York, NY 10013"], "country": "US", "state": "NY", "address3": "", "address2": null, "address1": "380 Broome St", "city": "New York", "zip_code": "10013"}, "is_closed": false, "review_count": 542, "coordinates": {"latitude": 40.7204631, "longitude": -73.9964956}, "id": "luannes-wild-ginger-all-asian-vegan-new-york", "image_url": "https://s3-media3.fl.yelpcdn.com/bphoto/tOJu4CNK4nwh5rrp8dxqWA/o.jpg", "categories": [{"alias": "vegetarian", "title": "Vegetarian"}, {"alias": "asianfusion", "title": "Asian Fusion"}, {"alias": "vegan", "title": "Vegan"}], "rating": 4.0}, {"transactions": ["delivery", "pickup"], "distance": 3767.26779585, "price": "$$", "display_phone": "(212) 255-5699", "phone": "+12122555699", "url": "https://www.yelp.com/biz/brunetti-pizza-new-york?adjust_creative=gBcvfFpabk3CnzmXKdYe3w&utm_campaign=yelp_api_v3&utm_medium=api_v3_business_search&utm_source=gBcvfFpabk3CnzmXKdYe3w", "name": "Brunetti Pizza", "location": {"display_address": ["626 Hudson St", "New York, NY 10014"], "country": "US", "state": "NY", "address3": "", "address2": null, "address1": "626 Hudson St", "city": "New York", "zip_code": "10014"}, "is_closed": false, "review_count": 202, "coordinates": {"latitude": 40.73829, "longitude": -74.0054}, "id": "brunetti-pizza-new-york", "image_url": "https://s3-media2.fl.yelpcdn.com/bphoto/fybRxT2KiiZASx6xM0VX_Q/o.jpg", "categories": [{"alias": "pizza", "title": "Pizza"}], "rating": 4.0}, {"transactions": [], "distance": 2147.649424072, "price": "$$$", "display_phone": "(212) 334-9020", "phone": "+12123349020", "url": "https://www.yelp.com/biz/aurora-soho-new-york?adjust_creative=gBcvfFpabk3CnzmXKdYe3w&utm_campaign=yelp_api_v3&utm_medium=api_v3_business_search&utm_source=gBcvfFpabk3CnzmXKdYe3w", "name": "Aurora Soho", "location": {"display_address": ["510 Broome St", "New York, NY 10013"], "country": "US", "state": "NY", "address3": "", "address2": "", "address1": "510 Broome St", "city": "New York", "zip_code": "10013"}, "is_closed": false, "review_count": 312, "coordinates": {"latitude": 40.723543, "longitude": -74.003199}, "id": "aurora-soho-new-york", "image_url": "https://s3-media2.fl.yelpcdn.com/bphoto/DDtqDnLCx3EMNb1aa17G8Q/o.jpg", "categories": [{"alias": "italian", "title": "Italian"}, {"alias": "breakfast_brunch", "title": "Breakfast & Brunch"}, {"alias": "wine_bars", "title": "Wine Bars"}], "rating": 4.0}, {"transactions": [], "distance": 3386.5261152999997, "price": "$$", "display_phone": "(347) 844-9588", "phone": "+13478449588", "url": "https://www.yelp.com/biz/emily-brooklyn?adjust_creative=gBcvfFpabk3CnzmXKdYe3w&utm_campaign=yelp_api_v3&utm_medium=api_v3_business_search&utm_source=gBcvfFpabk3CnzmXKdYe3w", "name": "Emily", "location": {"display_address": ["919 Fulton St", "Brooklyn, NY 11238"], "country": "US", "state": "NY", "address3": "", "address2": "", "address1": "919 Fulton St", "city": "Brooklyn", "zip_code": "11238"}, "is_closed": false, "review_count": 466, "coordinates": {"latitude": 40.6835192334848, "longitude": -73.9664132321178}, "id": "emily-brooklyn", "image_url": "https://s3-media2.fl.yelpcdn.com/bphoto/DP01taf4K5teDUJdBgegKw/o.jpg", "categories": [{"alias": "pizza", "title": "Pizza"}], "rating": 4.0}, {"transactions": [], "distance": 2554.368105298, "price": "$", "display_phone": "(646) 337-6755", "phone": "+16463376755", "url": "https://www.yelp.com/biz/feltmans-of-coney-island-new-york?adjust_creative=gBcvfFpabk3CnzmXKdYe3w&utm_campaign=yelp_api_v3&utm_medium=api_v3_business_search&utm_source=gBcvfFpabk3CnzmXKdYe3w", "name": "Feltman's of Coney Island", "location": {"display_address": ["80 Saint Marks Pl", "New York, NY 10003"], "country": "US", "state": "NY", "address3": null, "address2": "", "address1": "80 Saint Marks Pl", "city": "New York", "zip_code": "10003"}, "is_closed": false, "review_count": 27, "coordinates": {"latitude": 40.72765, "longitude": -73.98573}, "id": "feltmans-of-coney-island-new-york", "image_url": "https://s3-media3.fl.yelpcdn.com/bphoto/brOz0TpqfBDJamaQK2ai9Q/o.jpg", "categories": [{"alias": "hotdog", "title": "Hot Dogs"}], "rating": 4.5}, {"transactions": ["delivery", "pickup"], "distance": 1991.168145984, "price": "$$", "display_phone": "(212) 933-4587", "phone": "+12129334587", "url": "https://www.yelp.com/biz/mezetto-new-york?adjust_creative=gBcvfFpabk3CnzmXKdYe3w&utm_campaign=yelp_api_v3&utm_medium=api_v3_business_search&utm_source=gBcvfFpabk3CnzmXKdYe3w", "name": "Mezetto", "location": {"display_address": ["161 E Houston St", "New York, NY 10002"], "country": "US", "state": "NY", "address3": "", "address2": "", "address1": "161 E Houston St", "city": "New York", "zip_code": "10002"}, "is_closed": false, "review_count": 399, "coordinates": {"latitude": 40.7228863781236, "longitude": -73.9889362576721}, "id": "mezetto-new-york", "image_url": "https://s3-media4.fl.yelpcdn.com/bphoto/8umJoH1eA--OANB9kb3J0A/o.jpg", "categories": [{"alias": "mediterranean", "title": "Mediterranean"}, {"alias": "seafood", "title": "Seafood"}, {"alias": "breakfast_brunch", "title": "Breakfast & Brunch"}], "rating": 4.0}, {"transactions": [], "distance": 2594.2005577699997, "price": "$$", "display_phone": "", "phone": "", "url": "https://www.yelp.com/biz/good-night-sonny-new-york?adjust_creative=gBcvfFpabk3CnzmXKdYe3w&utm_campaign=yelp_api_v3&utm_medium=api_v3_business_search&utm_source=gBcvfFpabk3CnzmXKdYe3w", "name": "Good Night Sonny", "location": {"display_address": ["134 1st Ave", "New York, NY 10009"], "country": "US", "state": "NY", "address3": "", "address2": "", "address1": "134 1st Ave", "city": "New York", "zip_code": "10009"}, "is_closed": false, "review_count": 114, "coordinates": {"latitude": 40.7276866115628, "longitude": -73.9850075927549}, "id": "good-night-sonny-new-york", "image_url": "https://s3-media3.fl.yelpcdn.com/bphoto/1KPLl6ZNdDaMhLXjiaTAcw/o.jpg", "categories": [{"alias": "cocktailbars", "title": "Cocktail Bars"}, {"alias": "seafood", "title": "Seafood"}], "rating": 4.0}, {"transactions": [], "distance": 662.7741220518, "price": "$$$", "display_phone": "(718) 834-1776", "phone": "+17188341776", "url": "https://www.yelp.com/biz/henrys-end-restaurant-brooklyn-3?adjust_creative=gBcvfFpabk3CnzmXKdYe3w&utm_campaign=yelp_api_v3&utm_medium=api_v3_business_search&utm_source=gBcvfFpabk3CnzmXKdYe3w", "name": "Henry's End Restaurant", "location": {"display_address": ["44 Henry St", "Brooklyn, NY 11201"], "country": "US", "state": "NY", "address3": "", "address2": "", "address1": "44 Henry St", "city": "Brooklyn", "zip_code": "11201"}, "is_closed": false, "review_count": 284, "coordinates": {"latitude": 40.6997, "longitude": -73.99217}, "id": "henrys-end-restaurant-brooklyn-3", "image_url": "https://s3-media1.fl.yelpcdn.com/bphoto/gYN0_4TwvFrdait3-gqYqw/o.jpg", "categories": [{"alias": "newamerican", "title": "American (New)"}, {"alias": "diners", "title": "Diners"}, {"alias": "wine_bars", "title": "Wine Bars"}], "rating": 4.0}, {"transactions": ["delivery", "pickup"], "distance": 5390.9767880399995, "price": "$$", "display_phone": "(718) 361-7802", "phone": "+17183617802", "url": "https://www.yelp.com/biz/kavala-estiatorio-long-island-city-2?adjust_creative=gBcvfFpabk3CnzmXKdYe3w&utm_campaign=yelp_api_v3&utm_medium=api_v3_business_search&utm_source=gBcvfFpabk3CnzmXKdYe3w", "name": "Kavala Estiatorio", "location": {"display_address": ["1007 50th Ave", "Long Island City, NY 11101"], "country": "US", "state": "NY", "address3": "", "address2": "", "address1": "1007 50th Ave", "city": "Long Island City", "zip_code": "11101"}, "is_closed": false, "review_count": 127, "coordinates": {"latitude": 40.742855, "longitude": -73.95359}, "id": "kavala-estiatorio-long-island-city-2", "image_url": "https://s3-media4.fl.yelpcdn.com/bphoto/b7ZONvfEoCdbzkI-RmY1yA/o.jpg", "categories": [{"alias": "greek", "title": "Greek"}, {"alias": "venues", "title": "Venues & Event Spaces"}], "rating": 4.5}, {"transactions": [], "distance": 2959.494505528, "price": "$$", "display_phone": "(212) 206-0594", "phone": "+12122060594", "url": "https://www.yelp.com/biz/lelabar-new-york?adjust_creative=gBcvfFpabk3CnzmXKdYe3w&utm_campaign=yelp_api_v3&utm_medium=api_v3_business_search&utm_source=gBcvfFpabk3CnzmXKdYe3w", "name": "Lelabar", "location": {"display_address": ["422 Hudson St", "New York, NY 10014"], "country": "US", "state": "NY", "address3": "", "address2": "", "address1": "422 Hudson St", "city": "New York", "zip_code": "10014"}, "is_closed": false, "review_count": 306, "coordinates": {"latitude": 40.730384, "longitude": -74.006554}, "id": "lelabar-new-york", "image_url": "https://s3-media4.fl.yelpcdn.com/bphoto/oPRRilgoL35v82WrecQzzA/o.jpg", "categories": [{"alias": "wine_bars", "title": "Wine Bars"}, {"alias": "lounges", "title": "Lounges"}], "rating": 4.0}, {"transactions": [], "distance": 1538.9755191962, "price": "$", "display_phone": "(212) 760-8888", "phone": "+12127608888", "url": "https://www.yelp.com/biz/naya-express-new-york-21?adjust_creative=gBcvfFpabk3CnzmXKdYe3w&utm_campaign=yelp_api_v3&utm_medium=api_v3_business_search&utm_source=gBcvfFpabk3CnzmXKdYe3w", "name": "Naya Express", "location": {"display_address": ["One New York Plz", "New York, NY 10004"], "country": "US", "state": "NY", "address3": "", "address2": "", "address1": "One New York Plz", "city": "New York", "zip_code": "10004"}, "is_closed": false, "review_count": 49, "coordinates": {"latitude": 40.7023139, "longitude": -74.0114968}, "id": "naya-express-new-york-21", "image_url": "https://s3-media4.fl.yelpcdn.com/bphoto/FWKIff9-x9pIDQLU7r2Iug/o.jpg", "categories": [{"alias": "lebanese", "title": "Lebanese"}], "rating": 4.5}, {"transactions": [], "distance": 2410.83799086, "price": "$$$", "display_phone": "(212) 473-7348", "phone": "+12124737348", "url": "https://www.yelp.com/biz/pegu-club-new-york?adjust_creative=gBcvfFpabk3CnzmXKdYe3w&utm_campaign=yelp_api_v3&utm_medium=api_v3_business_search&utm_source=gBcvfFpabk3CnzmXKdYe3w", "name": "Pegu Club", "location": {"display_address": ["77 W Houston St", "New York, NY 10012"], "country": "US", "state": "NY", "address3": "", "address2": "", "address1": "77 W Houston St", "city": "New York", "zip_code": "10012"}, "is_closed": false, "review_count": 845, "coordinates": {"latitude": 40.726728, "longitude": -73.999755}, "id": "pegu-club-new-york", "image_url": "https://s3-media1.fl.yelpcdn.com/bphoto/6GZgmNGHwl6c6iTVX_JTVA/o.jpg", "categories": [{"alias": "lounges", "title": "Lounges"}, {"alias": "cocktailbars", "title": "Cocktail Bars"}, {"alias": "newamerican", "title": "American (New)"}], "rating": 4.0}, {"transactions": [], "distance": 4621.582394302, "price": "$$", "display_phone": "(347) 955-4100", "phone": "+13479554100", "url": "https://www.yelp.com/biz/le-paris-dakar-new-york?adjust_creative=gBcvfFpabk3CnzmXKdYe3w&utm_campaign=yelp_api_v3&utm_medium=api_v3_business_search&utm_source=gBcvfFpabk3CnzmXKdYe3w", "name": "Le Paris Dakar", "location": {"display_address": ["518 Nostrand Ave", "New York, NY 11216"], "country": "US", "state": "NY", "address3": "", "address2": null, "address1": "518 Nostrand Ave", "city": "New York", "zip_code": "11216"}, "is_closed": false, "review_count": 122, "coordinates": {"latitude": 40.6811617534164, "longitude": -73.9498048730164}, "id": "le-paris-dakar-new-york", "image_url": "https://s3-media4.fl.yelpcdn.com/bphoto/fV08jCi3kXckvqiKG6FUgQ/o.jpg", "categories": [{"alias": "desserts", "title": "Desserts"}, {"alias": "coffee", "title": "Coffee & Tea"}, {"alias": "bakeries", "title": "Bakeries"}], "rating": 4.5}, {"transactions": [], "distance": 3212.0593361740002, "price": "$$", "display_phone": "(212) 505-3700", "phone": "+12125053700", "url": "https://www.yelp.com/biz/doughnut-plant-brooklyn?adjust_creative=gBcvfFpabk3CnzmXKdYe3w&utm_campaign=yelp_api_v3&utm_medium=api_v3_business_search&utm_source=gBcvfFpabk3CnzmXKdYe3w", "name": "Doughnut Plant", "location": {"display_address": ["245 Flatbush Ave", "Brooklyn, NY 11217"], "country": "US", "state": "NY", "address3": "", "address2": "", "address1": "245 Flatbush Ave", "city": "Brooklyn", "zip_code": "11217"}, "is_closed": false, "review_count": 346, "coordinates": {"latitude": 40.680653, "longitude": -73.9747427}, "id": "doughnut-plant-brooklyn", "image_url": "https://s3-media3.fl.yelpcdn.com/bphoto/mF9TksptPsioN7K2TLiO4g/o.jpg", "categories": [{"alias": "donuts", "title": "Donuts"}, {"alias": "coffee", "title": "Coffee & Tea"}], "rating": 4.0}, {"transactions": [], "distance": 1658.1990795979998, "price": "$", "display_phone": "(646) 524-6353", "phone": "+16465246353", "url": "https://www.yelp.com/biz/spreadhouse-cafe-new-york-3?adjust_creative=gBcvfFpabk3CnzmXKdYe3w&utm_campaign=yelp_api_v3&utm_medium=api_v3_business_search&utm_source=gBcvfFpabk3CnzmXKdYe3w", "name": "Spreadhouse Cafe", "location": {"display_address": ["116 Suffolk St", "New York, NY 10002"], "country": "US", "state": "NY", "address3": "", "address2": "", "address1": "116 Suffolk St", "city": "New York", "zip_code": "10002"}, "is_closed": false, "review_count": 249, "coordinates": {"latitude": 40.71891, "longitude": -73.98585}, "id": "spreadhouse-cafe-new-york-3", "image_url": "https://s3-media2.fl.yelpcdn.com/bphoto/PF16a6PlYBY_vYt1lVkd1w/o.jpg", "categories": [{"alias": "coffee", "title": "Coffee & Tea"}, {"alias": "cafes", "title": "Cafes"}, {"alias": "wine_bars", "title": "Wine Bars"}], "rating": 4.0}, {"transactions": [], "distance": 2680.7516676399996, "price": "$", "display_phone": "(646) 543-9215", "phone": "+16465439215", "url": "https://www.yelp.com/biz/the-uncommons-new-york?adjust_creative=gBcvfFpabk3CnzmXKdYe3w&utm_campaign=yelp_api_v3&utm_medium=api_v3_business_search&utm_source=gBcvfFpabk3CnzmXKdYe3w", "name": "The Uncommons", "location": {"display_address": ["230 Thompson St", "New York, NY 10012"], "country": "US", "state": "NY", "address3": "", "address2": null, "address1": "230 Thompson St", "city": "New York", "zip_code": "10012"}, "is_closed": false, "review_count": 218, "coordinates": {"latitude": 40.729331, "longitude": -73.998649}, "id": "the-uncommons-new-york", "image_url": "https://s3-media4.fl.yelpcdn.com/bphoto/g6DDQisBT0GKvdPowaNxWw/o.jpg", "categories": [{"alias": "coffee", "title": "Coffee & Tea"}, {"alias": "tabletopgames", "title": "Tabletop Games"}], "rating": 4.0}, {"transactions": ["delivery", "pickup"], "distance": 2928.083246474, "price": "$$", "display_phone": "(718) 486-5150", "phone": "+17184865150", "url": "https://www.yelp.com/biz/quinoa-kitchen-brooklyn?adjust_creative=gBcvfFpabk3CnzmXKdYe3w&utm_campaign=yelp_api_v3&utm_medium=api_v3_business_search&utm_source=gBcvfFpabk3CnzmXKdYe3w", "name": "Quinoa Kitchen", "location": {"display_address": ["287 Bedford Ave", "Brooklyn, NY 11211"], "country": "US", "state": "NY", "address3": "", "address2": "", "address1": "287 Bedford Ave", "city": "Brooklyn", "zip_code": "11211"}, "is_closed": false, "review_count": 65, "coordinates": {"latitude": 40.71403, "longitude": -73.96147}, "id": "quinoa-kitchen-brooklyn", "image_url": "https://s3-media2.fl.yelpcdn.com/bphoto/da4zo_w9YVYLsKpR_Gt_kQ/o.jpg", "categories": [{"alias": "juicebars", "title": "Juice Bars & Smoothies"}, {"alias": "breakfast_brunch", "title": "Breakfast & Brunch"}, {"alias": "burgers", "title": "Burgers"}], "rating": 4.5}, {"transactions": ["delivery"], "distance": 6297.32971726, "price": "$$", "display_phone": "(212) 207-8302", "phone": "+12122078302", "url": "https://www.yelp.com/biz/omars-kitchen-and-bakery-new-york?adjust_creative=gBcvfFpabk3CnzmXKdYe3w&utm_campaign=yelp_api_v3&utm_medium=api_v3_business_search&utm_source=gBcvfFpabk3CnzmXKdYe3w", "name": "Omar's Kitchen & Bakery", "location": {"display_address": ["154 E 55th St", "New York, NY 10022"], "country": "US", "state": "NY", "address3": "", "address2": "", "address1": "154 E 55th St", "city": "New York", "zip_code": "10022"}, "is_closed": false, "review_count": 401, "coordinates": {"latitude": 40.7590294, "longitude": -73.9692688}, "id": "omars-kitchen-and-bakery-new-york", "image_url": "https://s3-media4.fl.yelpcdn.com/bphoto/U3-7G8iGrHkx9rrha_torQ/o.jpg", "categories": [{"alias": "halal", "title": "Halal"}, {"alias": "mideastern", "title": "Middle Eastern"}, {"alias": "mediterranean", "title": "Mediterranean"}], "rating": 4.5}, {"transactions": [], "distance": 4997.718304706, "price": "$$", "display_phone": "(718) 499-5623", "phone": "+17184995623", "url": "https://www.yelp.com/biz/lot-2-brooklyn-2?adjust_creative=gBcvfFpabk3CnzmXKdYe3w&utm_campaign=yelp_api_v3&utm_medium=api_v3_business_search&utm_source=gBcvfFpabk3CnzmXKdYe3w", "name": "Lot 2", "location": {"display_address": ["687 6th Ave", "Brooklyn, NY 11215"], "country": "US", "state": "NY", "address3": "", "address2": "", "address1": "687 6th Ave", "city": "Brooklyn", "zip_code": "11215"}, "is_closed": false, "review_count": 235, "coordinates": {"latitude": 40.6605911254883, "longitude": -73.9903106689453}, "id": "lot-2-brooklyn-2", "image_url": "https://s3-media1.fl.yelpcdn.com/bphoto/ZA6vLach2ScIUzmnVG13Zg/o.jpg", "categories": [{"alias": "newamerican", "title": "American (New)"}, {"alias": "burgers", "title": "Burgers"}], "rating": 4.5}, {"transactions": ["delivery", "pickup"], "distance": 4035.8948053000004, "price": "$$", "display_phone": "(212) 597-9999", "phone": "+12125979999", "url": "https://www.yelp.com/biz/patrizias-pizza-and-pasta-new-york?adjust_creative=gBcvfFpabk3CnzmXKdYe3w&utm_campaign=yelp_api_v3&utm_medium=api_v3_business_search&utm_source=gBcvfFpabk3CnzmXKdYe3w", "name": "Patrizia's Pizza and Pasta", "location": {"display_address": ["462-466 2nd Ave", "New York, NY 10016"], "country": "US", "state": "NY", "address3": "", "address2": "", "address1": "462-466 2nd Ave", "city": "New York", "zip_code": "10016"}, "is_closed": false, "review_count": 239, "coordinates": {"latitude": 40.7398415, "longitude": -73.9792862}, "id": "patrizias-pizza-and-pasta-new-york", "image_url": "https://s3-media2.fl.yelpcdn.com/bphoto/nh_FyZC6o69J5ORc5uTImA/o.jpg", "categories": [{"alias": "italian", "title": "Italian"}, {"alias": "pizza", "title": "Pizza"}, {"alias": "catering", "title": "Caterers"}], "rating": 4.5}, {"transactions": [], "distance": 4041.91132289, "price": "$$", "display_phone": "(347) 463-9231", "phone": "+13474639231", "url": "https://www.yelp.com/biz/bellocq-tea-atelier-brooklyn-2?adjust_creative=gBcvfFpabk3CnzmXKdYe3w&utm_campaign=yelp_api_v3&utm_medium=api_v3_business_search&utm_source=gBcvfFpabk3CnzmXKdYe3w", "name": "Bellocq Tea Atelier", "location": {"display_address": ["104 West St", "Brooklyn, NY 11222"], "country": "US", "state": "NY", "address3": "", "address2": "", "address1": "104 West St", "city": "Brooklyn", "zip_code": "11222"}, "is_closed": false, "review_count": 36, "coordinates": {"latitude": 40.7301765, "longitude": -73.9591417}, "id": "bellocq-tea-atelier-brooklyn-2", "image_url": "https://s3-media1.fl.yelpcdn.com/bphoto/erqVTeoffulMy1nJ_TMAeg/o.jpg", "categories": [{"alias": "coffee", "title": "Coffee & Tea"}], "rating": 4.5}, {"transactions": [], "distance": 4263.93989264, "price": "$", "display_phone": "(718) 768-6107", "phone": "+17187686107", "url": "https://www.yelp.com/biz/la-bagel-delight-brooklyn-4?adjust_creative=gBcvfFpabk3CnzmXKdYe3w&utm_campaign=yelp_api_v3&utm_medium=api_v3_business_search&utm_source=gBcvfFpabk3CnzmXKdYe3w", "name": "La Bagel Delight", "location": {"display_address": ["284 7th Ave", "Brooklyn, NY 11215"], "country": "US", "state": "NY", "address3": "", "address2": "", "address1": "284 7th Ave", "city": "Brooklyn", "zip_code": "11215"}, "is_closed": false, "review_count": 226, "coordinates": {"latitude": 40.668548813868, "longitude": -73.980512840055}, "id": "la-bagel-delight-brooklyn-4", "image_url": "https://s3-media3.fl.yelpcdn.com/bphoto/0scWS5fGj6BUasXZ28xlrw/o.jpg", "categories": [{"alias": "bagels", "title": "Bagels"}, {"alias": "salad", "title": "Salad"}, {"alias": "breakfast_brunch", "title": "Breakfast & Brunch"}], "rating": 4.0}, {"transactions": [], "distance": 1420.5855647275998, "price": "$", "display_phone": "(212) 625-8888", "phone": "+12126258888", "url": "https://www.yelp.com/biz/12-corners-new-york-4?adjust_creative=gBcvfFpabk3CnzmXKdYe3w&utm_campaign=yelp_api_v3&utm_medium=api_v3_business_search&utm_source=gBcvfFpabk3CnzmXKdYe3w", "name": "12 Corners", "location": {"display_address": ["121 Mott St", "New York, NY 10013"], "country": "US", "state": "NY", "address3": "", "address2": "", "address1": "121 Mott St", "city": "New York", "zip_code": "10013"}, "is_closed": false, "review_count": 109, "coordinates": {"latitude": 40.718048, "longitude": -73.997222}, "id": "12-corners-new-york-4", "image_url": "https://s3-media1.fl.yelpcdn.com/bphoto/W3xtkJZdCbT3BGj9Rw_SmA/o.jpg", "categories": [{"alias": "coffee", "title": "Coffee & Tea"}], "rating": 4.5}, {"transactions": ["delivery", "pickup"], "distance": 2466.759015312, "price": "$$", "display_phone": "(212) 673-7200", "phone": "+12126737200", "url": "https://www.yelp.com/biz/giano-restaurant-new-york?adjust_creative=gBcvfFpabk3CnzmXKdYe3w&utm_campaign=yelp_api_v3&utm_medium=api_v3_business_search&utm_source=gBcvfFpabk3CnzmXKdYe3w", "name": "Giano Restaurant", "location": {"display_address": ["126 E 7th St", "New York, NY 10009"], "country": "US", "state": "NY", "address3": "", "address2": "", "address1": "126 E 7th St", "city": "New York", "zip_code": "10009"}, "is_closed": false, "review_count": 427, "coordinates": {"latitude": 40.7262256596862, "longitude": -73.9840574049125}, "id": "giano-restaurant-new-york", "image_url": "https://s3-media1.fl.yelpcdn.com/bphoto/0PrOZ5stl86k6V1SzHcjNA/o.jpg", "categories": [{"alias": "italian", "title": "Italian"}], "rating": 4.0}, {"transactions": [], "distance": 6543.2690560599995, "price": "$$$$", "display_phone": "(212) 245-4388", "phone": "+12122454388", "url": "https://www.yelp.com/biz/il-tinello-ristorante-italiano-new-york?adjust_creative=gBcvfFpabk3CnzmXKdYe3w&utm_campaign=yelp_api_v3&utm_medium=api_v3_business_search&utm_source=gBcvfFpabk3CnzmXKdYe3w", "name": "Il Tinello Ristorante Italiano", "location": {"display_address": ["16 W 56th St", "New York, NY 10019"], "country": "US", "state": "NY", "address3": "", "address2": "", "address1": "16 W 56th St", "city": "New York", "zip_code": "10019"}, "is_closed": false, "review_count": 168, "coordinates": {"latitude": 40.76256, "longitude": -73.97566}, "id": "il-tinello-ristorante-italiano-new-york", "image_url": "https://s3-media3.fl.yelpcdn.com/bphoto/CYl-_D7OUNP0UgGrXj8RVA/o.jpg", "categories": [{"alias": "italian", "title": "Italian"}], "rating": 4.5}, {"transactions": ["pickup"], "distance": 4337.555932259999, "price": "$$", "display_phone": "(646) 869-6068", "phone": "+16468696068", "url": "https://www.yelp.com/biz/perpetuum-cafe-new-york?adjust_creative=gBcvfFpabk3CnzmXKdYe3w&utm_campaign=yelp_api_v3&utm_medium=api_v3_business_search&utm_source=gBcvfFpabk3CnzmXKdYe3w", "name": "Perpetuum Cafe", "location": {"display_address": ["124 W 25th St", "New York, NY 10001"], "country": "US", "state": "NY", "address3": "", "address2": "", "address1": "124 W 25th St", "city": "New York", "zip_code": "10001"}, "is_closed": false, "review_count": 63, "coordinates": {"latitude": 40.744445, "longitude": -73.993072}, "id": "perpetuum-cafe-new-york", "image_url": "https://s3-media4.fl.yelpcdn.com/bphoto/pgmYGuCFGv0s5X4FT0ndIg/o.jpg", "categories": [{"alias": "coffee", "title": "Coffee & Tea"}], "rating": 4.5}, {"transactions": ["delivery", "pickup"], "distance": 1215.4046926356, "price": "$", "display_phone": "(212) 226-8803", "phone": "+12122268803", "url": "https://www.yelp.com/biz/yaya-tea-garden-new-york-3?adjust_creative=gBcvfFpabk3CnzmXKdYe3w&utm_campaign=yelp_api_v3&utm_medium=api_v3_business_search&utm_source=gBcvfFpabk3CnzmXKdYe3w", "name": "Yaya Tea Garden", "location": {"display_address": ["51 Chrystie St", "New York, NY 10002"], "country": "US", "state": "NY", "address3": "", "address2": "", "address1": "51 Chrystie St", "city": "New York", "zip_code": "10002"}, "is_closed": false, "review_count": 377, "coordinates": {"latitude": 40.7162999, "longitude": -73.99496}, "id": "yaya-tea-garden-new-york-3", "image_url": "https://s3-media3.fl.yelpcdn.com/bphoto/Au1hvV3hKHZytvSCKh3oEg/o.jpg", "categories": [{"alias": "coffee", "title": "Coffee & Tea"}, {"alias": "japanese", "title": "Japanese"}, {"alias": "bubbletea", "title": "Bubble Tea"}], "rating": 4.0}, {"transactions": [], "distance": 3714.9473477799997, "price": "$$$", "display_phone": "(212) 620-0225", "phone": "+12126200225", "url": "https://www.yelp.com/biz/yakiniku-futago-new-york?adjust_creative=gBcvfFpabk3CnzmXKdYe3w&utm_campaign=yelp_api_v3&utm_medium=api_v3_business_search&utm_source=gBcvfFpabk3CnzmXKdYe3w", "name": "Yakiniku Futago", "location": {"display_address": ["37 W 17th St", "New York, NY 10011"], "country": "US", "state": "NY", "address3": "", "address2": "", "address1": "37 W 17th St", "city": "New York", "zip_code": "10011"}, "is_closed": false, "review_count": 144, "coordinates": {"latitude": 40.738851870947, "longitude": -73.9941236398979}, "id": "yakiniku-futago-new-york", "image_url": "https://s3-media2.fl.yelpcdn.com/bphoto/wJ2f_QF8LgnbkpwG5mwh4w/o.jpg", "categories": [{"alias": "japanese", "title": "Japanese"}, {"alias": "bbq", "title": "Barbeque"}, {"alias": "steak", "title": "Steakhouses"}], "rating": 4.5}, {"transactions": [], "distance": 4327.764546766, "price": "$$$$", "display_phone": "(212) 989-8883", "phone": "+12129898883", "url": "https://www.yelp.com/biz/morimoto-new-york?adjust_creative=gBcvfFpabk3CnzmXKdYe3w&utm_campaign=yelp_api_v3&utm_medium=api_v3_business_search&utm_source=gBcvfFpabk3CnzmXKdYe3w", "name": "Morimoto", "location": {"display_address": ["88 10th Ave", "New York, NY 10011"], "country": "US", "state": "NY", "address3": "", "address2": null, "address1": "88 10th Ave", "city": "New York", "zip_code": "10011"}, "is_closed": false, "review_count": 2536, "coordinates": {"latitude": 40.74312, "longitude": -74.007185}, "id": "morimoto-new-york", "image_url": "https://s3-media1.fl.yelpcdn.com/bphoto/Pd5n3jWDdaUMQFWT-0pNSQ/o.jpg", "categories": [{"alias": "japanese", "title": "Japanese"}, {"alias": "sushi", "title": "Sushi Bars"}], "rating": 4.0}, {"transactions": [], "distance": 1421.2684398764, "price": "$$$", "display_phone": "(212) 228-7732", "phone": "+12122287732", "url": "https://www.yelp.com/biz/dirt-candy-new-york-2?adjust_creative=gBcvfFpabk3CnzmXKdYe3w&utm_campaign=yelp_api_v3&utm_medium=api_v3_business_search&utm_source=gBcvfFpabk3CnzmXKdYe3w", "name": "Dirt Candy", "location": {"display_address": ["86 Allen St", "New York, NY 10002"], "country": "US", "state": "NY", "address3": "", "address2": "", "address1": "86 Allen St", "city": "New York", "zip_code": "10002"}, "is_closed": false, "review_count": 367, "coordinates": {"latitude": 40.7179222, "longitude": -73.9907108}, "id": "dirt-candy-new-york-2", "image_url": "https://s3-media2.fl.yelpcdn.com/bphoto/nLvIW6uN9k6lTXbcRm2MYw/o.jpg", "categories": [{"alias": "vegetarian", "title": "Vegetarian"}, {"alias": "vegan", "title": "Vegan"}], "rating": 4.0}, {"transactions": [], "distance": 2945.2998048599998, "price": "$", "display_phone": "(212) 555-1212", "phone": "+12125551212", "url": "https://www.yelp.com/biz/skinny-dennis-brooklyn?adjust_creative=gBcvfFpabk3CnzmXKdYe3w&utm_campaign=yelp_api_v3&utm_medium=api_v3_business_search&utm_source=gBcvfFpabk3CnzmXKdYe3w", "name": "Skinny Dennis", "location": {"display_address": ["152 Metropolitan Ave", "Brooklyn, NY 11211"], "country": "US", "state": "NY", "address3": "", "address2": "", "address1": "152 Metropolitan Ave", "city": "Brooklyn", "zip_code": "11211"}, "is_closed": false, "review_count": 172, "coordinates": {"latitude": 40.715863, "longitude": -73.962168}, "id": "skinny-dennis-brooklyn", "image_url": "https://s3-media2.fl.yelpcdn.com/bphoto/Qb6FQ2xkMPbuHBmeMprMfw/o.jpg", "categories": [{"alias": "bars", "title": "Bars"}, {"alias": "musicvenues", "title": "Music Venues"}], "rating": 4.0}, {"transactions": [], "distance": 4763.83308344, "price": "$$", "display_phone": "(212) 229-1700", "phone": "+12122291700", "url": "https://www.yelp.com/biz/le-pif-new-york-8?adjust_creative=gBcvfFpabk3CnzmXKdYe3w&utm_campaign=yelp_api_v3&utm_medium=api_v3_business_search&utm_source=gBcvfFpabk3CnzmXKdYe3w", "name": "Le Pif", "location": {"display_address": ["465 W 23rd St", "New York, NY 10011"], "country": "US", "state": "NY", "address3": "", "address2": "", "address1": "465 W 23rd St", "city": "New York", "zip_code": "10011"}, "is_closed": false, "review_count": 76, "coordinates": {"latitude": 40.7476868, "longitude": -74.0037054}, "id": "le-pif-new-york-8", "image_url": "https://s3-media4.fl.yelpcdn.com/bphoto/FwCloZIBzmuAyrRFfDs5ig/o.jpg", "categories": [{"alias": "wine_bars", "title": "Wine Bars"}, {"alias": "breakfast_brunch", "title": "Breakfast & Brunch"}, {"alias": "french", "title": "French"}], "rating": 4.5}, {"transactions": [], "distance": 2336.037637934, "price": "$$$", "display_phone": "(212) 965-9100", "phone": "+12129659100", "url": "https://www.yelp.com/biz/cocotte-new-york?adjust_creative=gBcvfFpabk3CnzmXKdYe3w&utm_campaign=yelp_api_v3&utm_medium=api_v3_business_search&utm_source=gBcvfFpabk3CnzmXKdYe3w", "name": "Cocotte", "location": {"display_address": ["110 Thompson St", "New York, NY 10012"], "country": "US", "state": "NY", "address3": "", "address2": "", "address1": "110 Thompson St", "city": "New York", "zip_code": "10012"}, "is_closed": false, "review_count": 248, "coordinates": {"latitude": 40.7256965637207, "longitude": -74.0016860961914}, "id": "cocotte-new-york", "image_url": "https://s3-media2.fl.yelpcdn.com/bphoto/8HoVqz5bFVwlPFHIF6EE6g/o.jpg", "categories": [{"alias": "french", "title": "French"}, {"alias": "basque", "title": "Basque"}], "rating": 4.0}, {"transactions": [], "distance": 5072.926625322, "price": "$$$$", "display_phone": "(212) 947-3636", "phone": "+12129473636", "url": "https://www.yelp.com/biz/keens-steakhouse-new-york?adjust_creative=gBcvfFpabk3CnzmXKdYe3w&utm_campaign=yelp_api_v3&utm_medium=api_v3_business_search&utm_source=gBcvfFpabk3CnzmXKdYe3w", "name": "Keens Steakhouse", "location": {"display_address": ["72 W 36th St", "New York, NY 10018"], "country": "US", "state": "NY", "address3": "", "address2": "", "address1": "72 W 36th St", "city": "New York", "zip_code": "10018"}, "is_closed": false, "review_count": 1758, "coordinates": {"latitude": 40.750713, "longitude": -73.986518}, "id": "keens-steakhouse-new-york", "image_url": "https://s3-media2.fl.yelpcdn.com/bphoto/FfrkvCd9EK5Q88Td6A9s-A/o.jpg", "categories": [{"alias": "steak", "title": "Steakhouses"}], "rating": 4.0}, {"transactions": ["delivery", "pickup"], "distance": 1814.120951102, "price": "$", "display_phone": "(212) 533-4252", "phone": "+12125334252", "url": "https://www.yelp.com/biz/stanton-pizza-new-york-2?adjust_creative=gBcvfFpabk3CnzmXKdYe3w&utm_campaign=yelp_api_v3&utm_medium=api_v3_business_search&utm_source=gBcvfFpabk3CnzmXKdYe3w", "name": "Stanton Pizza", "location": {"display_address": ["127 Stanton St", "New York, NY 10002"], "country": "US", "state": "NY", "address3": "", "address2": "", "address1": "127 Stanton St", "city": "New York", "zip_code": "10002"}, "is_closed": false, "review_count": 176, "coordinates": {"latitude": 40.720726, "longitude": -73.986709}, "id": "stanton-pizza-new-york-2", "image_url": "https://s3-media1.fl.yelpcdn.com/bphoto/g-t6TMTRxDjDTj0Tx8nv9w/o.jpg", "categories": [{"alias": "pizza", "title": "Pizza"}, {"alias": "italian", "title": "Italian"}], "rating": 4.0}, {"transactions": [], "distance": 2989.2653643199997, "price": "$$", "display_phone": "(347) 463-9886", "phone": "+13474639886", "url": "https://www.yelp.com/biz/the-shanti-shack-brooklyn?adjust_creative=gBcvfFpabk3CnzmXKdYe3w&utm_campaign=yelp_api_v3&utm_medium=api_v3_business_search&utm_source=gBcvfFpabk3CnzmXKdYe3w", "name": "The Shanti Shack", "location": {"display_address": ["85 N 3rd St", "Brooklyn, NY 11211"], "country": "US", "state": "NY", "address3": "", "address2": "", "address1": "85 N 3rd St", "city": "Brooklyn", "zip_code": "11211"}, "is_closed": false, "review_count": 21, "coordinates": {"latitude": 40.7172774, "longitude": -73.9624474}, "id": "the-shanti-shack-brooklyn", "image_url": "https://s3-media3.fl.yelpcdn.com/bphoto/NxfslO3MwM1VO0uk8ZB6kA/o.jpg", "categories": [{"alias": "vegetarian", "title": "Vegetarian"}, {"alias": "juicebars", "title": "Juice Bars & Smoothies"}], "rating": 5.0}, {"transactions": [], "distance": 4601.027742888, "price": "$$", "display_phone": "(646) 704-6149", "phone": "+16467046149", "url": "https://www.yelp.com/biz/pino-wine-bar-new-york?adjust_creative=gBcvfFpabk3CnzmXKdYe3w&utm_campaign=yelp_api_v3&utm_medium=api_v3_business_search&utm_source=gBcvfFpabk3CnzmXKdYe3w", "name": "Pino Wine Bar", "location": {"display_address": ["156 E 33rd St", "New York, NY 10016"], "country": "US", "state": "NY", "address3": "", "address2": "", "address1": "156 E 33rd St", "city": "New York", "zip_code": "10016"}, "is_closed": false, "review_count": 103, "coordinates": {"latitude": 40.7452456, "longitude": -73.9793704}, "id": "pino-wine-bar-new-york", "image_url": "https://s3-media4.fl.yelpcdn.com/bphoto/bT-0svB_5Cn_33Q-0CfsUw/o.jpg", "categories": [{"alias": "wine_bars", "title": "Wine Bars"}, {"alias": "tradamerican", "title": "American (Traditional)"}, {"alias": "breakfast_brunch", "title": "Breakfast & Brunch"}], "rating": 4.5}, {"transactions": [], "distance": 3612.1546176959996, "price": "$$$", "display_phone": "(212) 243-4020", "phone": "+12122434020", "url": "https://www.yelp.com/biz/union-square-cafe-new-york-3?adjust_creative=gBcvfFpabk3CnzmXKdYe3w&utm_campaign=yelp_api_v3&utm_medium=api_v3_business_search&utm_source=gBcvfFpabk3CnzmXKdYe3w", "name": "Union Square Cafe", "location": {"display_address": ["101 E 19th St", "New York, NY 10003"], "country": "US", "state": "NY", "address3": "", "address2": "", "address1": "101 E 19th St", "city": "New York", "zip_code": "10003"}, "is_closed": false, "review_count": 899, "coordinates": {"latitude": 40.7375381, "longitude": -73.9876539}, "id": "union-square-cafe-new-york-3", "image_url": "https://s3-media3.fl.yelpcdn.com/bphoto/AsnlUCReDtHhaUMGFm1a4g/o.jpg", "categories": [{"alias": "newamerican", "title": "American (New)"}, {"alias": "cafes", "title": "Cafes"}, {"alias": "wine_bars", "title": "Wine Bars"}], "rating": 4.0}, {"transactions": [], "distance": 4417.733733862, "price": "$$", "display_phone": "(718) 483-9950", "phone": "+17184839950", "url": "https://www.yelp.com/biz/covenhoven-brooklyn?adjust_creative=gBcvfFpabk3CnzmXKdYe3w&utm_campaign=yelp_api_v3&utm_medium=api_v3_business_search&utm_source=gBcvfFpabk3CnzmXKdYe3w", "name": "Covenhoven", "location": {"display_address": ["730 Classon Ave", "Brooklyn, NY 11238"], "country": "US", "state": "NY", "address3": "", "address2": null, "address1": "730 Classon Ave", "city": "Brooklyn", "zip_code": "11238"}, "is_closed": false, "review_count": 79, "coordinates": {"latitude": 40.675246, "longitude": -73.960244}, "id": "covenhoven-brooklyn", "image_url": "https://s3-media2.fl.yelpcdn.com/bphoto/DUDTSCvSgAudOwSqpuDLZg/o.jpg", "categories": [{"alias": "bars", "title": "Bars"}], "rating": 4.5}], "total": 131358}